poleemploi_io_api/__init__.py
poleemploi_io_api/base/__init__.py
poleemploi_io_api/base/api.py
poleemploi_io_api/base/schemas.py
poleemploi_io_api/cache.py
poleemploi_io_api/rome/__init__.py
poleemploi_io_api/rome/v1/__init__.py
poleemploi_io_api/rome/v1/api.py
poleemploi_io_api/rome/v4/__init__.py
poleemploi_io_api/rome/v4/api.py
poleemploi_io_api/tests/__init__.py
poleemploi_io_api/tests/test_base.py
poleemploi_io_api/tests/test_cache.py
poleemploi_io_api/tests/test_rome_v1.py
poleemploi_io_api/tests/test_rome_v4.py
poleemploi_io_api-1.0.0.dist-info/METADATA
poleemploi_io_api-1.0.0.dist-info/WHEEL
poleemploi_io_api-1.0.0.dist-info/RECORD
