Metadata-Version: 2.1
Name: poleemploi-io-api
Version: 1.0.0
Summary: Python package to use poleemploi io api (requires account)
Home-page: https://github.com/StartupsPoleEmploi/poleemploi-io-api
License: GPL-3.0-only
Keywords: poleemploi,poleemploi_io,poleemploi_io_api
Author: La Bonne Boite
Author-email: labonneboite@pole-emploi.fr
Requires-Python: >=3.11,<4.0
Classifier: Development Status :: 5 - Production/Stable
Classifier: License :: OSI Approved :: GNU Affero General Public License v3
Classifier: License :: OSI Approved :: GNU General Public License v3 (GPLv3)
Classifier: Programming Language :: Python
Classifier: Programming Language :: Python :: 3
Classifier: Programming Language :: Python :: 3.11
Classifier: Programming Language :: Python :: 3.12
Classifier: Programming Language :: Python :: 3.13
Classifier: Programming Language :: Python :: 3.10
Requires-Dist: pydantic[email] (>=2.5.3,<3.0.0)
Requires-Dist: redis (>=5.0.3,<6.0.0)
Requires-Dist: requests (>=2.28.2,<3.0.0)
Requires-Dist: requests-cache (>=1.1.1,<2.0.0)
Project-URL: Repository, https://github.com/StartupsPoleEmploi/poleemploi-io-api
